airflow/upgrade/__init__.py
airflow/upgrade/checker.py
airflow/upgrade/config.py
airflow/upgrade/formatters.py
airflow/upgrade/problem.py
airflow/upgrade/version.py
airflow/upgrade/rules/__init__.py
airflow/upgrade/rules/aaa_airflow_version_check.py
airflow/upgrade/rules/airflow_macro_plugin_removed.py
airflow/upgrade/rules/base_rule.py
airflow/upgrade/rules/chain_between_dag_and_operator_not_allowed_rule.py
airflow/upgrade/rules/conn_id_is_unique.py
airflow/upgrade/rules/conn_type_is_not_nullable.py
airflow/upgrade/rules/custom_executors_require_full_path_rule.py
airflow/upgrade/rules/custom_operator_metaclass_rule.py
airflow/upgrade/rules/db_api_functions.py
airflow/upgrade/rules/fernet_enabled.py
airflow/upgrade/rules/fix_conf_not_importable_from_airflow.py
airflow/upgrade/rules/gcp_service_account_keys_rule.py
airflow/upgrade/rules/hostname_callable_rule.py
airflow/upgrade/rules/import_changes.py
airflow/upgrade/rules/legacy_ui_deprecated.py
airflow/upgrade/rules/logging_configuration.py
airflow/upgrade/rules/mesos_executor_removed.py
airflow/upgrade/rules/no_additional_args_in_operators.py
airflow/upgrade/rules/parsing_processes_configuration_rule.py
airflow/upgrade/rules/pod_template_file_rule.py
airflow/upgrade/rules/postgres_mysql_sqlite_version_upgrade_check.py
airflow/upgrade/rules/renamed_classes.py
airflow/upgrade/rules/send_grid_moved.py
airflow/upgrade/rules/spark_jdbc_operator_conn_id_rule.py
airflow/upgrade/rules/task_handlers_moved.py
airflow/upgrade/rules/use_customsqlainterface_class_rule.py
apache_airflow_upgrade_check-1.4.0.dist-info/LICENSE
apache_airflow_upgrade_check-1.4.0.dist-info/METADATA
apache_airflow_upgrade_check-1.4.0.dist-info/NOTICE
apache_airflow_upgrade_check-1.4.0.dist-info/WHEEL
apache_airflow_upgrade_check-1.4.0.dist-info/top_level.txt
apache_airflow_upgrade_check-1.4.0.dist-info/RECORD
