Metadata-Version: 2.1
Name: apache-airflow-upgrade-check
Version: 1.4.0
Summary: Check for compatibility between Airflow versions
Home-page: https://airflow.apache.org
Author: Apache Airflow PMC
Author-email: dev@airflow.apache.org
License: Apache License 2.0
Project-URL: Source Code, https://github.com/apache/airflow
Project-URL: Bug Tracker, https://github.com/apache/airflow/issues
Project-URL: Documentation, https://airflow.apache.org/docs/
Keywords: airflow,upgrade
Platform: UNKNOWN
Classifier: Development Status :: 5 - Production/Stable
Classifier: Intended Audience :: Developers
Classifier: License :: OSI Approved :: Apache Software License
Classifier: Programming Language :: Python :: 2.7
Classifier: Programming Language :: Python :: 3
Classifier: Programming Language :: Python :: 3.6
Classifier: Programming Language :: Python :: 3.7
Classifier: Programming Language :: Python :: 3.8
Requires-Python: !=3.0.*,!=3.1.*,!=3.2.*,!=3.3.*,!=3.4.*,>=2.7
